chucks/__about__.py
chucks/__init__.py
chucks/core.py
chucks/utils.py
chucks/cli/__init__.py
chucks-0.0.1.dist-info/METADATA
chucks-0.0.1.dist-info/WHEEL
chucks-0.0.1.dist-info/RECORD
