Metadata-Version: 2.3
Name: chucks
Version: 0.0.1
Project-URL: Documentation, https://github.com/fioccajohn/chucks#readme
Project-URL: Issues, https://github.com/fioccajohn/chucks/issues
Project-URL: Source, https://github.com/fioccajohn/chucks
Author-email: John Fiocca <fioccajohn@gmail.com>
Classifier: Development Status :: 4 - Beta
Classifier: Programming Language :: Python
Classifier: Programming Language :: Python :: 3.8
Classifier: Programming Language :: Python :: 3.9
Classifier: Programming Language :: Python :: 3.10
Classifier: Programming Language :: Python :: 3.11
Classifier: Programming Language :: Python :: 3.12
Classifier: Programming Language :: Python :: Implementation :: CPython
Classifier: Programming Language :: Python :: Implementation :: PyPy
Requires-Python: >=3.8
Requires-Dist: pandas
Requires-Dist: schwab-py
